rivescript_redis.py
rivescript_redis-0.1.0.dist-info/DESCRIPTION.rst
rivescript_redis-0.1.0.dist-info/METADATA
rivescript_redis-0.1.0.dist-info/RECORD
rivescript_redis-0.1.0.dist-info/WHEEL
rivescript_redis-0.1.0.dist-info/metadata.json
rivescript_redis-0.1.0.dist-info/top_level.txt
