Metadata-Version: 2.0
Name: rivescript-redis
Version: 0.1.0
Summary: Redis driver for RiveScript
Home-page: https://github.com/aichaos/rivescript-python
Author: Noah Petherbridge
Author-email: root@kirsle.net
License: MIT
Keywords: rivescript
Platform: UNKNOWN
Classifier: License :: OSI Approved :: MIT License
Classifier: Programming Language :: Python
Classifier: Programming Language :: Python :: 2
Classifier: Programming Language :: Python :: 3
Classifier: Development Status :: 3 - Alpha
Classifier: Intended Audience :: Developers
Classifier: Topic :: Scientific/Engineering :: Artificial Intelligence
Requires-Dist: setuptools
Requires-Dist: redis
Requires-Dist: rivescript
